{
    "status":0,
    "message": [
        {
            "id": 13,
            "title": "一季度多家房企利润跌幅超50%,去库存促销站打响",
            "add_time": "2015-04-05",
            "xhaiyao": "一季度多家房企利润跌幅超50%,去库存促销站打响",
            "click": 1,
            "img_url": "http://n.sinaimg.cn/news/transform/700/w1000h500/20190829/b18b-icxmqsv1672125.jpg"
        },
        {
            "id": 14,
            "title": "一季度多家房企利润跌幅超50%,去库存促销站打响",
            "add_time": "2015-04-05",
            "xhaiyao": "一季度多家房企利润跌幅超50%,去库存促销站打响",
            "click": 2,
            "img_url": "http://n.sinaimg.cn/news/transform/700/w1000h500/20190829/b18b-icxmqsv1672125.jpg"
        }
    ]
}